unittest_fixtures-2.3.0.dist-info/METADATA
unittest_fixtures-2.3.0.dist-info/WHEEL
unittest_fixtures-2.3.0.dist-info/entry_points.txt
unittest_fixtures-2.3.0.dist-info/licenses/LICENSE
unittest_fixtures/__init__.py
unittest_fixtures/fixtures.py
unittest_fixtures/parametrized.py
unittest_fixtures/py.typed
unittest_fixtures/types.py
unittest_fixtures-2.3.0.dist-info/RECORD
