Metadata-Version: 2.1
Name: unittest-fixtures
Version: 2.3.0
Summary: A small library for loading unittest fixtures
Author-Email: Albert Hopkins <marduk@letterboxes.org>
License: BSD-3
Project-URL: homepage, https://github.com/enku/unittest-fixtures
Project-URL: repository, https://github.com/enku/unittest-fixtures
Requires-Python: >=3.11
